fir_1d_pipeline.v
// ============================================================
// fir_1d_pipeline.v
// 5-Tap Pipelined FIR Digital Differentiator
// Coefficients: (1/8) * [-1, -2, 0, +2, +1]
//
// PURE PIPELINE — multipliers kept exactly as in direct-form.
// Only change from original: registers inserted between stages.
//
// Pipeline Stages:
//   Stage 1: Shift register (delay line)
//   Stage 2: Multiply each tap by its coefficient
//   Stage 3: Add all products + scale by 1/8
//
// Latency   : 3 clock cycles
// Throughput: 1 output per clock cycle
// Input     : 8-bit unsigned pixel
// Output    : 8-bit unsigned edge magnitude
// ============================================================

module fir_1d_pipeline (
    input  wire        clk,
    input  wire        rst_n,      // active-low synchronous reset
    input  wire        valid_in,
    input  wire [7:0]  x_in,       // 8-bit unsigned pixel

    output reg         valid_out,
    output reg  [7:0]  y_out       // 8-bit unsigned magnitude output
);

    // ----------------------------------------------------------
    // Coefficients: h = [-1, -2, 0, +2, +1]
    // Stored as signed integers (no scaling yet, /8 at the end)
    // ----------------------------------------------------------
    localparam signed [3:0] H0 = -1;
    localparam signed [3:0] H1 = -2;
    localparam signed [3:0] H2 =  0;
    localparam signed [3:0] H3 =  2;
    localparam signed [3:0] H4 =  1;

    // ----------------------------------------------------------
    // STAGE 1: Tapped Delay Line (shift register)
    // sr[0] = x[n], sr[1] = x[n-1], ..., sr[4] = x[n-4]
    // ----------------------------------------------------------
    reg [7:0] sr [0:4];
    reg       s1_valid;

    always @(posedge clk) begin
        if (!rst_n) begin
            sr[0] <= 8'd0; sr[1] <= 8'd0;
            sr[2] <= 8'd0; sr[3] <= 8'd0;
            sr[4] <= 8'd0;
            s1_valid <= 1'b0;
        end else begin
            s1_valid <= valid_in;
            if (valid_in) begin
                sr[0] <= x_in;
                sr[1] <= sr[0];
                sr[2] <= sr[1];
                sr[3] <= sr[2];
                sr[4] <= sr[3];
            end
        end
    end

    // ----------------------------------------------------------
    // STAGE 2: Multiply each tap by its coefficient
    // Input : 8-bit unsigned × 4-bit signed = 12-bit signed
    // p0 = H0 * x[n]   = -1 * x[n]
    // p1 = H1 * x[n-1] = -2 * x[n-1]
    // p2 = H2 * x[n-2] =  0 * x[n-2]  (always zero)
    // p3 = H3 * x[n-3] = +2 * x[n-3]
    // p4 = H4 * x[n-4] = +1 * x[n-4]
    // ----------------------------------------------------------
    reg signed [11:0] p0, p1, p2, p3, p4;
    reg               s2_valid;

    always @(posedge clk) begin
        if (!rst_n) begin
            p0 <= 12'sd0; p1 <= 12'sd0;
            p2 <= 12'sd0; p3 <= 12'sd0;
            p4 <= 12'sd0;
            s2_valid <= 1'b0;
        end else begin
            s2_valid <= s1_valid;
            // Sign-extend sr to signed before multiplying
            p0 <= H0 * $signed({1'b0, sr[0]});
            p1 <= H1 * $signed({1'b0, sr[1]});
            p2 <= H2 * $signed({1'b0, sr[2]});
            p3 <= H3 * $signed({1'b0, sr[3]});
            p4 <= H4 * $signed({1'b0, sr[4]});
        end
    end

    // ----------------------------------------------------------
    // STAGE 3: Add all products, scale by 1/8 (arithmetic >>3)
    // Sum range: max = 2*255 + 255 = 765, min = -765
    // Needs 11 bits signed. After >>3: fits in 8 bits.
    // Output: absolute value clipped to [0, 255]
    // ----------------------------------------------------------
    reg signed [11:0] sum;
    reg               s3_valid;

    always @(posedge clk) begin
        if (!rst_n) begin
            sum      <= 12'sd0;
            s3_valid <= 1'b0;
            valid_out <= 1'b0;
            y_out     <= 8'd0;
        end else begin
            s3_valid  <= s2_valid;
            sum       <= p0 + p1 + p2 + p3 + p4;

            valid_out <= s3_valid;
            if (s3_valid) begin
                // Divide by 8 (arithmetic right shift)
                // Then take absolute value → magnitude
                if (sum[11]) begin
                    // negative: negate then shift
                    y_out <= (~sum + 1'b1) >>> 3;
                end else begin
                    y_out <= sum >>> 3;
                end
            end else begin
                y_out <= 8'd0;
            end
        end
    end

endmodule

fir_2d_edge_pipeline.v
// ============================================================
// fir_2d_edge_pipeline.v
// 2D FIR Edge Detector — Top Level
// Uses fir_1d_pipeline (pure pipeline, multipliers kept)
//
// Edge Magnitude: |G(i,j)| = |Gx(i,j)| + |Gy(i,j)|
// Latency   : 3 cycles
// Throughput: 1 pixel/cycle
// ============================================================

module fir_2d_edge_pipeline (
    input  wire       clk,
    input  wire       rst_n,
    input  wire       valid_in,
    input  wire [7:0] pixel_in,

    output wire       valid_out,
    output reg  [7:0] edge_out
);

    // Horizontal gradient Gx
    wire       gx_valid;
    wire [7:0] gx_out;

    fir_1d_pipeline u_fir_row (
        .clk       (clk),
        .rst_n     (rst_n),
        .valid_in  (valid_in),
        .x_in      (pixel_in),
        .valid_out (gx_valid),
        .y_out     (gx_out)
    );

    // Vertical gradient Gy
    wire       gy_valid;
    wire [7:0] gy_out;

    fir_1d_pipeline u_fir_col (
        .clk       (clk),
        .rst_n     (rst_n),
        .valid_in  (valid_in),
        .x_in      (pixel_in),
        .valid_out (gy_valid),
        .y_out     (gy_out)
    );

    // Edge magnitude: |Gx| + |Gy|, saturate to 8-bit
    assign valid_out = gx_valid;

    wire [8:0] sum_mag = {1'b0, gx_out} + {1'b0, gy_out};

    always @(posedge clk) begin
        if (!rst_n)
            edge_out <= 8'd0;
        else if (valid_out)
            edge_out <= sum_mag[8] ? 8'd255 : sum_mag[7:0];
        else
            edge_out <= 8'd0;
    end

endmodule

tb_fir_2d_edge_pipeline.v
// ============================================================
// tb_fir_2d_edge_pipeline.v
// Testbench for fir_2d_edge_pipeline
// ============================================================

`timescale 1ns/1ps

module tb_fir_2d_edge_pipeline;

    reg        clk, rst_n, valid_in;
    reg  [7:0] pixel_in;
    wire       valid_out;
    wire [7:0] edge_out;

    initial clk = 0;
    always #5 clk = ~clk;

    fir_2d_edge_pipeline u_dut (
        .clk       (clk),
        .rst_n     (rst_n),
        .valid_in  (valid_in),
        .pixel_in  (pixel_in),
        .valid_out (valid_out),
        .edge_out  (edge_out)
    );

    task apply_pixel;
        input [7:0] pix;
        begin
            @(negedge clk);
            valid_in = 1'b1;
            pixel_in = pix;
        end
    endtask

    task flush;
        integer i;
        begin
            @(negedge clk);
            valid_in = 1'b0;
            pixel_in = 8'd0;
            repeat(8) @(posedge clk);
        end
    endtask

    integer idx;

    initial begin
        $dumpfile("tb_fir_2d_edge_pipeline.vcd");
        $dumpvars(0, tb_fir_2d_edge_pipeline);

        rst_n = 0; valid_in = 0; pixel_in = 0;
        repeat(4) @(posedge clk);
        @(negedge clk); rst_n = 1;
        $display("\n[%0t] RESET RELEASED", $time);

        // TEST 1: Flat region — expect 0 after pipeline fills
        $display("\n[%0t] TEST 1: Flat region (pixel=100)", $time);
        for (idx = 0; idx < 10; idx = idx+1)
            apply_pixel(8'd100);
        flush;

        // TEST 2: Step edge 0 -> 200
        $display("\n[%0t] TEST 2: Step edge (0->200)", $time);
        for (idx = 0; idx < 5; idx = idx+1)
            apply_pixel(8'd0);
        for (idx = 0; idx < 8; idx = idx+1)
            apply_pixel(8'd200);
        flush;

        // TEST 3: Ramp — expect constant output in steady state
        $display("\n[%0t] TEST 3: Ramp (0,10,20,...,90)", $time);
        for (idx = 0; idx < 10; idx = idx+1)
            apply_pixel(idx * 10);
        flush;

        // TEST 4: Impulse — value 8 at n=0
        $display("\n[%0t] TEST 4: Impulse (value=8)", $time);
        for (idx = 0; idx < 5; idx = idx+1)
            apply_pixel(8'd0);
        apply_pixel(8'd8);
        for (idx = 0; idx < 8; idx = idx+1)
            apply_pixel(8'd0);
        flush;

        $display("\n[%0t] SIMULATION COMPLETE", $time);
        #20; $finish;
    end

    always @(posedge clk) begin
        if (valid_out)
            $display("[%0t]  pixel_in=%0d | edge_out=%0d", $time, pixel_in, edge_out);
    end

endmodule

tb_fir_2d_edge_pipeline.vcd
$date
	Wed Apr  8 08:30:37 2026
$end
$version
	Icarus Verilog
$end
$timescale
	1ps
$end
$scope module tb_fir_2d_edge_pipeline $end
$var wire 1 ! valid_out $end
$var wire 8 " edge_out [7:0] $end
$var reg 1 # clk $end
$var reg 8 $ pixel_in [7:0] $end
$var reg 1 % rst_n $end
$var reg 1 & valid_in $end
$var integer 32 ' idx [31:0] $end
$scope module u_dut $end
$var wire 1 # clk $end
$var wire 8 ( pixel_in [7:0] $end
$var wire 1 % rst_n $end
$var wire 1 & valid_in $end
$var wire 1 ! valid_out $end
$var wire 9 ) sum_mag [8:0] $end
$var wire 1 * gy_valid $end
$var wire 8 + gy_out [7:0] $end
$var wire 1 , gx_valid $end
$var wire 8 - gx_out [7:0] $end
$var reg 8 . edge_out [7:0] $end
$scope module u_fir_col $end
$var wire 1 # clk $end
$var wire 1 % rst_n $end
$var wire 1 & valid_in $end
$var wire 8 / x_in [7:0] $end
$var parameter 4 0 H0 $end
$var parameter 4 1 H1 $end
$var parameter 4 2 H2 $end
$var parameter 4 3 H3 $end
$var parameter 4 4 H4 $end
$var reg 12 5 p0 [11:0] $end
$var reg 12 6 p1 [11:0] $end
$var reg 12 7 p2 [11:0] $end
$var reg 12 8 p3 [11:0] $end
$var reg 12 9 p4 [11:0] $end
$var reg 1 : s1_valid $end
$var reg 1 ; s2_valid $end
$var reg 1 < s3_valid $end
$var reg 12 = sum [11:0] $end
$var reg 1 * valid_out $end
$var reg 8 > y_out [7:0] $end
$upscope $end
$scope module u_fir_row $end
$var wire 1 # clk $end
$var wire 1 % rst_n $end
$var wire 1 & valid_in $end
$var wire 8 ? x_in [7:0] $end
$var parameter 4 @ H0 $end
$var parameter 4 A H1 $end
$var parameter 4 B H2 $end
$var parameter 4 C H3 $end
$var parameter 4 D H4 $end
$var reg 12 E p0 [11:0] $end
$var reg 12 F p1 [11:0] $end
$var reg 12 G p2 [11:0] $end
$var reg 12 H p3 [11:0] $end
$var reg 12 I p4 [11:0] $end
$var reg 1 J s1_valid $end
$var reg 1 K s2_valid $end
$var reg 1 L s3_valid $end
$var reg 12 M sum [11:0] $end
$var reg 1 , valid_out $end
$var reg 8 N y_out [7:0] $end
$upscope $end
$upscope $end
$scope task apply_pixel $end
$var reg 8 O pix [7:0] $end
$upscope $end
$scope task flush $end
$upscope $end
$upscope $end
$enddefinitions $end
$comment Show the parameter values. $end
$dumpall
b1 D
b10 C
b0 B
b1110 A
b1111 @
b1 4
b10 3
b0 2
b1110 1
b1111 0
$end
#0
$dumpvars
bx O
bx N
bx M
xL
xK
xJ
bx I
bx H
bx G
bx F
bx E
b0 ?
bx >
bx =
x<
x;
x:
bx 9
bx 8
bx 7
bx 6
bx 5
b0 /
bx .
bx -
x,
bx +
x*
bx )
b0 (
bx '
0&
0%
b0 $
0#
bx "
x!
$end
#5000
b0 )
0J
0K
b0 I
b0 H
b0 G
b0 F
b0 E
b0 -
b0 N
0!
0,
0L
b0 M
0:
0;
b0 9
b0 8
b0 7
b0 6
b0 5
b0 +
b0 >
0*
0<
b0 =
b0 "
b0 .
1#
#10000
0#
#15000
1#
#20000
0#
#25000
1#
#30000
0#
#35000
1#
#40000
b1100100 O
b0 '
1%
0#
#45000
1#
#50000
b1 '
b1100100 $
b1100100 (
b1100100 /
b1100100 ?
1&
0#
#55000
1:
1J
1#
#60000
b10 '
0#
#65000
b111110011100 E
1K
b111110011100 5
1;
1#
#70000
b11 '
0#
#75000
b111110011100 =
1<
b111100111000 6
b111110011100 M
1L
b111100111000 F
1#
#80000
b100 '
0#
#85000
b11000 )
b1100 -
b1100 N
1!
1,
b111011010100 M
b1100 +
b1100 >
1*
b111011010100 =
1#
#90000
b101 '
0#
#95000
b1001010 )
b11000 "
b11000 .
b100101 +
b100101 >
b11001000 8
b100101 -
b100101 N
b11001000 H
1#
#100000
b110 '
0#
#105000
b1100100 I
b111110011100 M
b1100100 9
b111110011100 =
b1001010 "
b1001010 .
1#
#110000
b111 '
0#
#115000
b11000 )
b1100 +
b1100 >
b0 =
b1100 -
b1100 N
b0 M
1#
#120000
b1000 '
0#
#125000
b0 )
b0 -
b0 N
b0 +
b0 >
b11000 "
b11000 .
1#
#130000
b1001 '
0#
#135000
b0 "
b0 .
1#
#140000
b1010 '
0#
#145000
1#
#150000
b0 $
b0 (
b0 /
b0 ?
0&
0#
#155000
0:
0J
1#
#160000
0#
#165000
0K
0;
1#
#170000
0#
#175000
0<
0L
1#
#180000
0#
#185000
0!
0,
0*
1#
#190000
0#
#195000
1#
#200000
0#
#205000
1#
#210000
0#
#215000
1#
#220000
0#
#225000
b0 O
b0 '
1#
#230000
b1 '
1&
0#
#235000
1:
1J
1#
#240000
b10 '
0#
#245000
b0 E
1K
b0 5
1;
1#
#250000
b11 '
0#
#255000
b1100100 =
1<
b0 6
b1100100 M
1L
b0 F
1#
#260000
b100 '
0#
#265000
b11000 )
b1100 -
b1100 N
1!
1,
b100101100 M
b1100 +
b1100 >
1*
b100101100 =
1#
#270000
b11001000 O
b0 '
0#
#275000
b1001010 )
b11000 "
b11000 .
b100101 +
b100101 >
b0 8
b100101 -
b100101 N
b0 H
1#
#280000
b1 '
b11001000 $
b11001000 (
b11001000 /
b11001000 ?
0#
#285000
b0 I
b1100100 M
b0 9
b1100100 =
b1001010 "
b1001010 .
1#
#290000
b10 '
0#
#295000
b11000 )
b1100 +
b1100 >
b0 =
b111100111000 5
b1100 -
b1100 N
b0 M
b111100111000 E
1#
#300000
b11 '
0#
#305000
b0 )
b111001110000 F
b0 -
b0 N
b111100111000 M
b111001110000 6
b0 +
b0 >
b111100111000 =
b11000 "
b11000 .
1#
#310000
b100 '
0#
#315000
b110010 )
b0 "
b0 .
b11001 +
b11001 >
b110110101000 =
b11001 -
b11001 N
b110110101000 M
1#
#320000
b101 '
0#
#325000
b10010110 )
b110010000 H
b1001011 -
b1001011 N
b110010000 8
b1001011 +
b1001011 >
b110010 "
b110010 .
1#
#330000
b110 '
0#
#335000
b10010110 "
b10010110 .
b111100111000 =
b11001000 9
b111100111000 M
b11001000 I
1#
#340000
b111 '
0#
#345000
b110010 )
b11001 -
b11001 N
b0 M
b11001 +
b11001 >
b0 =
1#
#350000
b1000 '
0#
#355000
b0 )
b110010 "
b110010 .
b0 +
b0 >
b0 -
b0 N
1#
#360000
b0 $
b0 (
b0 /
b0 ?
0&
0#
#365000
0J
0:
b0 "
b0 .
1#
#370000
0#
#375000
0;
0K
1#
#380000
0#
#385000
0L
0<
1#
#390000
0#
#395000
0*
0!
0,
1#
#400000
0#
#405000
1#
#410000
0#
#415000
1#
#420000
0#
#425000
1#
#430000
0#
#435000
b0 O
b0 '
1#
#440000
b1010 O
b1 '
1&
0#
#445000
1J
1:
1#
#450000
b10100 O
b10 '
b1010 $
b1010 (
b1010 /
b1010 ?
0#
#455000
b0 5
1;
b0 E
1K
1#
#460000
b11110 O
b11 '
b10100 $
b10100 (
b10100 /
b10100 ?
0#
#465000
b0 F
b111111110110 E
b11001000 M
1L
b0 6
b111111110110 5
b11001000 =
1<
1#
#470000
b101000 O
b100 '
b11110 $
b11110 (
b11110 /
b11110 ?
0#
#475000
b110010 )
b11001 +
b11001 >
1*
b1001001110 =
b111111101100 6
b111111101100 5
b11001 -
b11001 N
1!
1,
b1001001110 M
b111111101100 F
b111111101100 E
1#
#480000
b110010 O
b101 '
b101000 $
b101000 (
b101000 /
b101000 ?
0#
#485000
b10010010 )
b0 H
b111111011000 F
b111111100010 E
b1001001 -
b1001001 N
b1000110000 M
b0 8
b111111011000 6
b111111100010 5
b1001001 +
b1001001 >
b1000110000 =
b110010 "
b110010 .
1#
#490000
b111100 O
b110 '
b110010 $
b110010 (
b110010 /
b110010 ?
0#
#495000
b10001100 )
b10010010 "
b10010010 .
b1000110 +
b1000110 >
b10000010 =
b0 9
b10100 8
b111111000100 6
b111111011000 5
b1000110 -
b1000110 N
b10000010 M
b0 I
b10100 H
b111111000100 F
b111111011000 E
1#
#500000
b1000110 O
b111 '
b111100 $
b111100 (
b111100 /
b111100 ?
0#
#505000
b100000 )
b1010 I
b101000 H
b111110110000 F
b111111001110 E
b10000 -
b10000 N
b111110110000 M
b1010 9
b101000 8
b111110110000 6
b111111001110 5
b10000 +
b10000 >
b111110110000 =
b10001100 "
b10001100 .
1#
#510000
b1010000 O
b1000 '
b1000110 $
b1000110 (
b1000110 /
b1000110 ?
0#
#515000
b10100 )
b100000 "
b100000 .
b1010 +
b1010 >
b10100 9
b111100 8
b111110011100 6
b111111000100 5
b1010 -
b1010 N
b10100 I
b111100 H
b111110011100 F
b111111000100 E
1#
#520000
b1011010 O
b1001 '
b1010000 $
b1010000 (
b1010000 /
b1010000 ?
0#
#525000
b11110 I
b1010000 H
b111110001000 F
b111110111010 E
b11110 9
b1010000 8
b111110001000 6
b111110111010 5
b10100 "
b10100 .
1#
#530000
b1010 '
b1011010 $
b1011010 (
b1011010 /
b1011010 ?
0#
#535000
b101000 9
b1100100 8
b111101110100 6
b111110110000 5
b101000 I
b1100100 H
b111101110100 F
b111110110000 E
1#
#540000
b0 $
b0 (
b0 /
b0 ?
0&
0#
#545000
0J
b110010 I
b1111000 H
b111101100000 F
b111110100110 E
0:
b110010 9
b1111000 8
b111101100000 6
b111110100110 5
1#
#550000
0#
#555000
0;
0K
1#
#560000
0#
#565000
0L
0<
1#
#570000
0#
#575000
b0 )
b0 +
b0 >
0*
b0 -
b0 N
0!
0,
1#
#580000
0#
#585000
b0 "
b0 .
1#
#590000
0#
#595000
1#
#600000
0#
#605000
1#
#610000
0#
#615000
b0 O
b0 '
1#
#620000
b1 '
1&
0#
#625000
1J
1:
1#
#630000
b10 '
0#
#635000
b111100 9
b10001100 8
b111101001100 6
b0 5
1;
b111100 I
b10001100 H
b111101001100 F
b0 E
1K
1#
#640000
b11 '
0#
#645000
b1000110 I
b10100000 H
b0 F
b10100 M
1L
b1000110 9
b10100000 8
b0 6
b10100 =
1<
1#
#650000
b100 '
0#
#655000
b100 )
b10 +
b10 >
1*
b11100110 =
b1010000 9
b10110100 8
b10 -
b10 N
1!
1,
b11100110 M
b1010000 I
b10110100 H
1#
#660000
b1000 O
b101 '
0#
#665000
b111000 )
b1011010 I
b0 H
b11100 -
b11100 N
b100000100 M
b1011010 9
b0 8
b11100 +
b11100 >
b100000100 =
b100 "
b100 .
1#
#670000
b0 O
b0 '
b1000 $
b1000 (
b1000 /
b1000 ?
0#
#675000
b1000000 )
b111000 "
b111000 .
b100000 +
b100000 >
b1011010 =
b0 9
b100000 -
b100000 N
b1011010 M
b0 I
1#
#680000
b1 '
b0 $
b0 (
b0 /
b0 ?
0#
#685000
b10110 )
b111111111000 E
b1011 -
b1011 N
b0 M
b111111111000 5
b1011 +
b1011 >
b0 =
b1000000 "
b1000000 .
1#
#690000
b10 '
0#
#695000
b0 )
b10110 "
b10110 .
b0 +
b0 >
b111111111000 =
b111111110000 6
b0 5
b0 -
b0 N
b111111111000 M
b111111110000 F
b0 E
1#
#700000
b11 '
0#
#705000
b10 )
b0 F
b1 -
b1 N
b111111110000 M
b0 6
b1 +
b1 >
b111111110000 =
b0 "
b0 .
1#
#710000
b100 '
0#
#715000
b100 )
b10 "
b10 .
b10 +
b10 >
b0 =
b10000 8
b10 -
b10 N
b0 M
b10000 H
1#
#720000
b101 '
0#
#725000
b0 )
b1000 I
b0 H
b0 -
b0 N
b10000 M
b1000 9
b0 8
b0 +
b0 >
b10000 =
b100 "
b100 .
1#
#730000
b110 '
0#
#735000
b100 )
b0 "
b0 .
b10 +
b10 >
b1000 =
b0 9
b10 -
b10 N
b1000 M
b0 I
1#
#740000
b111 '
0#
#745000
b10 )
b1 -
b1 N
b0 M
b1 +
b1 >
b0 =
b100 "
b100 .
1#
#750000
b1000 '
0#
#755000
b0 )
b10 "
b10 .
b0 +
b0 >
b0 -
b0 N
1#
#760000
0&
0#
#765000
0J
0:
b0 "
b0 .
1#
#770000
0#
#775000
0;
0K
1#
#780000
0#
#785000
0L
0<
1#
#790000
0#
#795000
0*
0!
0,
1#
